G4SNP/G4Hunter.py
G4SNP/__init__.py
G4SNP/snp_overlap.py
G4SNP-1.0.0.dist-info/LICENSE.txt
G4SNP-1.0.0.dist-info/METADATA
G4SNP-1.0.0.dist-info/WHEEL
G4SNP-1.0.0.dist-info/top_level.txt
G4SNP-1.0.0.dist-info/RECORD
