Metadata-Version: 2.1
Name: G4SNP
Version: 1.0.0
Summary: This code finds the distances of SNPs relative to the start codon based on their mRNA positions then executes G4Hunter tool and extracts the closest G4 sequences from the SNPs for several genes. 
Home-page: https://github.com/Marc-shebaby/Capstone-Project.git
Author: Marc Shebaby
Author-email: marc_shebaby@lau.edu
Classifier: Programming Language :: Python :: 3.9
Classifier: License :: OSI Approved :: MIT License
Classifier: Operating System :: OS Independent
License-File: LICENSE.txt
Requires-Dist: numpy
Requires-Dist: pandas
Requires-Dist: Bio
